{
  "type": "FeatureCollection",
  "features": [
    {
      "type": "Feature",
      "properties": { "name": "OPTIMIZED_SERVER", "marker-color": "#ff0000" },
      "geometry": { "type": "Point", "coordinates": [28.5914, 42.9306] }
    },
    {
      "type": "Feature",
      "properties": { "weight": 500 },
      "geometry": { "type": "Point", "coordinates": [-0.1, 51.5] }
    },
    {
      "type": "Feature",
      "properties": { "weight": 800 },
      "geometry": { "type": "Point", "coordinates": [-74, 40.7] }
    },
    {
      "type": "Feature",
      "properties": { "weight": 700 },
      "geometry": { "type": "Point", "coordinates": [139.6, 35.6] }
    },
    {
      "type": "Feature",
      "properties": { "weight": 300 },
      "geometry": { "type": "Point", "coordinates": [151.2, -33.8] }
    },
    {
      "type": "Feature",
      "properties": { "weight": 400 },
      "geometry": { "type": "Point", "coordinates": [-43.1, -22.9] }
    },
    {
      "type": "Feature",
      "properties": { "weight": 300 },
      "geometry": { "type": "Point", "coordinates": [3.4, 6.5] }
    },
    {
      "type": "Feature",
      "properties": { "weight": 600 },
      "geometry": { "type": "Point", "coordinates": [72.8, 19] }
    }
  ]
}